{
  "date": "2026-03-26",
  "activity": "Competitive Weeknight Paddle",
  "start_time": "2026-03-26T17:45:00",
  "going_count": 18,
  "going": [
    "Amy Lockwood",
    "Anna Tosick",
    "Brandon Carr",
    "Clare Waterloo",
    "Deirdre Reilly",
    "Deven Clemens",
    "Dylan Turner",
    "Fred Andersen",
    "Gary Serrano",
    "John Kaplanis",
    "Kat Alvarado",
    "Lauren Holtz",
    "Lisa Tarantino",
    "Michelle Turner",
    "Nancy Rogers",
    "Nicole Sholly",
    "Poppy Nelson-Smith",
    "Susie Abel"
  ]
}