{
  "date": "2026-06-20",
  "activity": "Competitive Saturday Paddle",
  "start_time": "2026-06-20T09:00:00",
  "going_count": 24,
  "going": [
    "Amy Lockwood",
    "Deirdre Reilly",
    "Dylan Turner",
    "Elaine Steinbrecher",
    "Fred Andersen",
    "Gary Serrano",
    "John Kaplanis",
    "Josh Luria",
    "Karl Burch",
    "Lauren Holtz",
    "Lisa Tarantino",
    "Lynn Curry",
    "Matt Huizingh",
    "Mia Rocca",
    "Michelle Turner",
    "Nancy Rogers",
    "Nicole Sholly",
    "Roberto Reichard",
    "Roxann Bettencourt",
    "Steve Gies",
    "Steve Herzog",
    "Susie Abel",
    "Toni Anderson",
    "Tracy Turner"
  ]
}